shinigami/__init__.py
shinigami/cli.py
shinigami/utils.py
crc_shinigami-0.6.1.dist-info/LICENSE.md
crc_shinigami-0.6.1.dist-info/METADATA
crc_shinigami-0.6.1.dist-info/WHEEL
crc_shinigami-0.6.1.dist-info/entry_points.txt
crc_shinigami-0.6.1.dist-info/RECORD
