Metadata-Version: 2.1
Name: crc-shinigami
Version: 0.6.1
Summary: A stand alone Python application for killing errant processes on Slurm based compute nodes.
Home-page: https://github.com/pitt-crc/shinigami
Keywords: process,terminate,slurm
Author: Pitt Center for Research Computing
Requires-Python: >=3.9.0,<4.0.0
Classifier: Environment :: Console
Classifier: Intended Audience :: System Administrators
Classifier: License :: OSI Approved :: GNU General Public License v3 (GPLv3)
Classifier: Natural Language :: English
Classifier: Operating System :: POSIX :: Linux
Classifier: Programming Language :: Python :: 3
Classifier: Programming Language :: Python :: 3.9
Classifier: Programming Language :: Python :: 3.10
Classifier: Programming Language :: Python :: 3.11
Classifier: Programming Language :: Python :: 3.12
Classifier: Typing :: Typed
Requires-Dist: asyncssh[bcrypt,fido2] (>=2.13.2,<3.0.0)
Requires-Dist: pandas (==2.2.3)
Requires-Dist: pydantic (>=2.0.3,<3.0.0)
Requires-Dist: pydantic-settings (>=2.0.2,<3.0.0)
Project-URL: Repository, https://github.com/pitt-crc/shinigami
